django_mongoengine_filter/__init__.py
django_mongoengine_filter/compat.py
django_mongoengine_filter/fields.py
django_mongoengine_filter/filters.py
django_mongoengine_filter/filterset.py
django_mongoengine_filter/views.py
django_mongoengine_filter/widgets.py
django_mongoengine_filter/locale/fr/LC_MESSAGES/django.po
tests/dfm_app/__init__.py
tests/dfm_app/constants.py
tests/dfm_app/documents.py
tests/dfm_app/filters.py
tests/dfm_app/views.py
tests/dfm_app/templates/dfm_app/person_list.html
tests/factories/__init__.py
tests/factories/person.py
tests/settings/__init__.py
tests/settings/base.py
tests/settings/dev.py
tests/settings/helpers.py
tests/settings/test.py
django_mongoengine_filter-0.4.2.dist-info/LICENSE_GPL2.0.txt
django_mongoengine_filter-0.4.2.dist-info/LICENSE_LGPL_2.1.txt
django_mongoengine_filter-0.4.2.dist-info/METADATA
django_mongoengine_filter-0.4.2.dist-info/WHEEL
django_mongoengine_filter-0.4.2.dist-info/top_level.txt
django_mongoengine_filter-0.4.2.dist-info/RECORD
