Metadata-Version: 2.1
Name: django-mongoengine-filter
Version: 0.4.2
Summary: django-mongoengine-filter is a reusable Django application inspired from django-filter for allowing mongoengine users to filter querysets dynamically.
Home-page: https://github.com/barseghyanartur/django-mongoengine-filter
Author: Artur Barseghyhan
Author-email: artur.barseghyan@gmail.com
License: GPL-2.0-only OR LGPL-2.1-or-later
Project-URL: Bug Tracker, https://github.com/barseghyanartur/django-mongoengine-filter/issues
Project-URL: Documentation, https://django-mongoengine-filter.readthedocs.io/
Project-URL: Source Code, https://github.com/barseghyanartur/django-mongoengine-filter
Project-URL: Changelog, https://django-mongoengine-filter.readthedocs.io/en/latest/changelog.html
Keywords: mongoengine,django-filter
Classifier: Development Status :: 4 - Beta
Classifier: Environment :: Web Environment
Classifier: Intended Audience :: Developers
Classifier: License :: OSI Approved :: GNU General Public License v2 (GPLv2)
Classifier: License :: OSI Approved :: GNU Lesser General Public License v2 or later (LGPLv2+)
Classifier: Operating System :: OS Independent
Classifier: Programming Language :: Python
Classifier: Programming Language :: Python :: 3.7
Classifier: Programming Language :: Python :: 3.8
Classifier: Programming Language :: Python :: 3.9
Classifier: Programming Language :: Python :: 3.10
Classifier: Programming Language :: Python :: 3.11
Classifier: Framework :: Django
Requires-Python: >=3.7
License-File: LICENSE_GPL2.0.txt
License-File: LICENSE_LGPL_2.1.txt
Requires-Dist: six (>=1.9)
